[
  {
    "ContainingType": "Trace.Controllers.CreateAccountController",
    "Method": "CreateAccount",
    "RelativePath": "accounts",
    "HttpMethod": "POST",
    "IsController": true,
    "Order": 0,
    "Parameters": [
      {
        "Name": "account",
        "Type": "Core.Models.Account",
        "IsRequired": true
      }
    ],
    "ReturnTypes": []
  },
  {
    "ContainingType": "Trace.Controllers.GroupAccountsController",
    "Method": "Post",
    "RelativePath": "api/GroupAccounts",
    "HttpMethod": "POST",
    "IsController": true,
    "Order": 0,
    "Parameters": [
      {
        "Name": "groupAccount",
        "Type": "Core.Models.GroupAccount",
        "IsRequired": true
      }
    ],
    "ReturnTypes": []
  },
  {
    "ContainingType": "Trace.Controllers.GroupAccountsController",
    "Method": "GetAllGroupAccounts",
    "RelativePath": "api/GroupAccounts",
    "HttpMethod": "GET",
    "IsController": true,
    "Order": 0,
    "Parameters": [],
    "ReturnTypes": []
  },
  {
    "ContainingType": "Trace.Controllers.TransactionsController",
    "Method": "RecordTransaction",
    "RelativePath": "api/Transactions",
    "HttpMethod": "POST",
    "IsController": true,
    "Order": 0,
    "Parameters": [
      {
        "Name": "transaction",
        "Type": "Core.Models.Transaction",
        "IsRequired": true
      }
    ],
    "ReturnTypes": []
  },
  {
    "ContainingType": "Trace.Controllers.CreateAccountController",
    "Method": "GetAllAccounts",
    "RelativePath": "GetAccounts",
    "HttpMethod": "GET",
    "IsController": true,
    "Order": 0,
    "Parameters": [],
    "ReturnTypes": []
  }
]